{
  "db_name": "SQLite",
  "query": "\n        SELECT *\n        FROM romfiles\n        WHERE id = ?\n        ",
  "describe": {
    "columns": [
      {
        "name": "id",
        "ordinal": 0,
        "type_info": "Int64"
      },
      {
        "name": "path",
        "ordinal": 1,
        "type_info": "Text"
      },
      {
        "name": "size",
        "ordinal": 2,
        "type_info": "Int64"
      }
    ],
    "parameters": {
      "Right": 1
    },
    "nullable": [
      false,
      false,
      false
    ]
  },
  "hash": "5b3d774d597a94d1550f998dd0e5a9ea76296034cb75ac31c9bd7fbfbfbd6590"
}
